tsm/__init__.py
tsm/__main__.py
tsm/main.py
ts_machine-2021.4.4.dist-info/LICENSE
ts_machine-2021.4.4.dist-info/METADATA
ts_machine-2021.4.4.dist-info/WHEEL
ts_machine-2021.4.4.dist-info/entry_points.txt
ts_machine-2021.4.4.dist-info/top_level.txt
ts_machine-2021.4.4.dist-info/RECORD
