Metadata-Version: 2.1
Name: ts-machine
Version: 2021.4.4
Summary: no longer working
Home-page: https://github.com/gcrtnst/ts_machine
Author: gcrtnst
License: MIT
Project-URL: Source, https://github.com/gcrtnst/ts_machine
Project-URL: Tracker, https://github.com/gcrtnst/ts_machine/issues
Platform: UNKNOWN
Requires-Python: ~=3.7
